canonicalwebteam/__init__.py
canonicalwebteam/candid/__init__.py
canonicalwebteam/candid/client.py
canonicalwebteam/candid/exceptions.py
canonicalwebteam.candid-0.9.0.dist-info/LICENSE
canonicalwebteam.candid-0.9.0.dist-info/WHEEL
canonicalwebteam.candid-0.9.0.dist-info/METADATA
canonicalwebteam.candid-0.9.0.dist-info/RECORD
