Metadata-Version: 2.1
Name: canonicalwebteam.candid
Version: 0.9.0
Summary: 
License: LGPL-3.0
Author: Canonical Web Team
Author-email: webteam@canonical.com
Requires-Python: >=3.6,<4.0
Classifier: License :: OSI Approved :: GNU Lesser General Public License v3 (LGPLv3)
Classifier: Programming Language :: Python :: 3
Classifier: Programming Language :: Python :: 3.6
Classifier: Programming Language :: Python :: 3.7
Classifier: Programming Language :: Python :: 3.8
Requires-Dist: pymacaroons (==0.13.0)
Requires-Dist: requests (>=2.25.1,<3.0.0)
